bib2x/__init__.py
bib2x/bib2x.py
bib2x/tex.db
bib2x/texfile.py
bib2x/texhandler/__init__.py
bib2x/texhandler/handler.py
bib2x/texhandler/html.py
bib2x/texhandler/json.py
bib2x/texhandler/memory.py
tests/__init__.py
tests/test_bib2x_html.py
tests/test_bib2x_json.py
tests/test_bib2x_main.py
bib2x-0.4.2.dist-info/LICENSE
bib2x-0.4.2.dist-info/METADATA
bib2x-0.4.2.dist-info/WHEEL
bib2x-0.4.2.dist-info/entry_points.txt
bib2x-0.4.2.dist-info/top_level.txt
bib2x-0.4.2.dist-info/RECORD
