Metadata-Version: 2.1
Name: bib2x
Version: 0.4.2
Summary: A BibTex parser and converter
Home-page: http://bib2x.readthedocs.org/
Download-URL: http://pypi.python.org/pypi/bib2x
Author: dkrajzew
Author-email: d.krajzewicz@gmail.com
License: BSD
Project-URL: Documentation, https://bib2x.readthedocs.io/
Project-URL: Source, https://github.com/dkrajzew/bib2x
Project-URL: Tracker, https://github.com/dkrajzew/bib2x/issues
Project-URL: Discussions, https://github.com/dkrajzew/bib2x/discussions
Classifier: Development Status :: 5 - Production/Stable
Classifier: Environment :: Console
Classifier: Programming Language :: Python
Classifier: Programming Language :: Python :: 3
Classifier: License :: OSI Approved :: BSD License
Classifier: Operating System :: OS Independent
Classifier: Intended Audience :: Developers
Classifier: Intended Audience :: Information Technology
Classifier: Intended Audience :: System Administrators
Classifier: Intended Audience :: Telecommunications Industry
Classifier: Topic :: Software Development :: Libraries :: Python Modules
Classifier: Topic :: Software Development :: Localization
Classifier: Topic :: Text Processing :: Markup :: HTML
Classifier: Topic :: Other/Nonlisted Topic
Classifier: Topic :: Artistic Software
Requires-Python: >=3, <4
License-File: LICENSE
